{
    "CheckWellbeingTask": [
        "كيف تشعر اليوم؟",
        "هل أنت بخير؟",
        "كيف كانت صحتك اليوم؟",
        "كيف الحال"
    ],
    "askHelpingTask": [
        "هل يمكننك مساعدتى؟"
    ],
    "MathTask": [
        "هل ضعف مستواي في الرياضيات يؤثر؟",
        "هل يمكن أن يعيقني ضعفي في الرياضيات؟"
    ],
    "DifficultyTask": [
        "هل يعتبر علم الحاسوب صعبًا؟",
        "كيف تقارن بين التخصصات من حيث الصعوبة؟",
        "ما مدى صعوبة برنامج علم الحاسوب؟"
    ],
    "MaterialsTypeTask": [
        "ما أنواع المصادر التي تستخدم؟",
        "أي محتوى رئيسي يتضمنه هذا البرنامج؟",
        "ما هي الموارد التي تدرس فيها؟"
    ],
    "HighGpaTask": [
        "ما الذي يمكن أن يساعدني في الحصول على معدل مرتفع؟",
        "هل تؤدي دراستي إلى سجل أكاديمي قوي؟",
        "كيف أحقق درجة تراكمي مرتفعة؟"
    ],
    "ChooseDepartmentTask": [
        "كيف أختار التخصص المناسب؟",
        "ما العوامل التي تحدد أفضل برنامج؟",
        "ما المعايير لاختيار القسم؟"
    ],
    "TypesOfProgramsTask": [
        "ما البرامج المتاحة؟",
        "أي قسم يجب أن أنضم إليه؟",
        "ماذا عن الفروع المختلفة؟",
        "ما أنواع البرامج في الرياضيات؟"
    ],
    "ExternalCoursesTask": [
        "متى يجب أخذ دورات خارجية؟",
        "أي مهارات يفضل أن أركز عليها؟",
        "ماذا عن الدورات المعينة المطلوبة؟",
        "متى يُنصح بالتخصص في مهارة معينة؟"
    ],
    "CourseQueryTask": [
        "ما المقرر الذي أدرسه؟",
        "أي مادة تشمل هذا الموضوع؟",
        "ما الوحدة المناسبة لهذا الدرس؟",
        "أي موضوع يندرج تحت هذه المادة؟"
    ],
    "ProfessorQueryTask": [
        "من هو أستاذ المادة؟",
        "مين الدكتور المسؤول عن هذا الدرس؟",
        "من هي الدكتورة التي تدرّس هذا المقرر؟",
        "من المعلم المختص؟"
    ],
    "PrerequisiteQueryTask": [
        "ما المتطلبات لهذه المادة؟",
        "ماذا يجب أن أكمل قبل المقرر؟",
        "هل هناك شروط للالتحاق؟",
        "ما المتطلبات الضرورية لهذه المادة؟"
    ],
    "ExamRecom": [
        "كيف يعمل نظام الامتحانات؟",
        "هل تم تصميم الامتحان بمستويات صعوبة مختلفة؟",
        "ما نمط الامتحانات المتبعة؟",
        "هل تتبع الامتحانات تصنيفات متفاوتة بالصعوبة؟"
    ]
}
